v6gen/__init__.py
v6gen/__main__.py
v6gen-0.1.0.dist-info/LICENSE
v6gen-0.1.0.dist-info/WHEEL
v6gen-0.1.0.dist-info/METADATA
v6gen-0.1.0.dist-info/RECORD
