Metadata-Version: 2.1
Name: v6gen
Version: 0.1.0
Summary: Simple tool for generating IPv6 addresses randomly or based by the hostname
License: MIT
Author: Michael Vieira
Author-email: contact@mvieira.fr
Requires-Python: >=3.8,<4.0
Classifier: License :: OSI Approved :: MIT License
Classifier: Programming Language :: Python :: 3
Classifier: Programming Language :: Python :: 3.8
